{
  "project_info": {
    "project_number": "726078885838",
    "firebase_url": "https://cookhub-53197.firebaseio.com",
    "project_id": "cookhub-53197",
    "storage_bucket": "cookhub-53197.appspot.com"
  },
  "client": [
    {
      "client_info": {
        "mobilesdk_app_id": "1:726078885838:android:c3daa642b7f02c47",
        "android_client_info": {
          "package_name": "com.example.android.cookhub"
        }
      },
      "oauth_client": [
        {
          "client_id": "726078885838-ss0bhat9rdbus8lg3umtm5idpb6odgk1.apps.googleusercontent.com",
          "client_type": 3
        }
      ],
      "api_key": [
        {
          "current_key": "AIzaSyB-mgByBWy9Mhckk_NAvYUhLnZ9CEW-nXQ"
        }
      ],
      "services": {
        "analytics_service": {
          "status": 1
        },
        "appinvite_service": {
          "status": 1,
          "other_platform_oauth_client": []
        },
        "ads_service": {
          "status": 2
        }
      }
    }
  ],
  "configuration_version": "1"
}